{
"2":[[{"context":[{"name":"yearInt","value":1980}],"value":{"name":"angelic","value":true},"expression":"147-8-147-37","instId":1},{"context":[{"name":"yearInt","value":80}],"value":{"name":"angelic","value":true},"expression":"147-8-147-37","instId":4},{"context":[{"name":"yearInt","value":89}],"value":{"name":"angelic","value":true},"expression":"147-8-147-37","instId":3},{"context":[{"name":"yearInt","value":1980}],"value":{"name":"angelic","value":true},"expression":"147-8-147-37","instId":6},{"context":[{"name":"yearInt","value":1980}],"value":{"name":"angelic","value":true},"expression":"147-8-147-37","instId":0},{"context":[{"name":"yearInt","value":2010}],"value":{"name":"angelic","value":false},"expression":"147-8-147-37","instId":9},{"context":[{"name":"yearInt","value":1980}],"value":{"name":"angelic","value":true},"expression":"147-8-147-37","instId":8},{"context":[{"name":"yearInt","value":1980}],"value":{"name":"angelic","value":true},"expression":"147-8-147-37","instId":2},{"context":[{"name":"yearInt","value":1980}],"value":{"name":"angelic","value":true},"expression":"147-8-147-37","instId":5},{"context":[{"name":"yearInt","value":1980}],"value":{"name":"angelic","value":true},"expression":"147-8-147-37","instId":7}],[{"context":[{"name":"yearInt","value":1980}],"value":{"name":"angelic","value":true},"expression":"147-8-147-37","instId":1},{"context":[{"name":"yearInt","value":80}],"value":{"name":"angelic","value":true},"expression":"147-8-147-37","instId":4},{"context":[{"name":"yearInt","value":89}],"value":{"name":"angelic","value":true},"expression":"147-8-147-37","instId":3},{"context":[{"name":"yearInt","value":1980}],"value":{"name":"angelic","value":true},"expression":"147-8-147-37","instId":6},{"context":[{"name":"yearInt","value":1980}],"value":{"name":"angelic","value":true},"expression":"147-8-147-37","instId":0},{"context":[{"name":"yearInt","value":2010}],"value":{"name":"angelic","value":true},"expression":"147-8-147-37","instId":9},{"context":[{"name":"yearInt","value":1980}],"value":{"name":"angelic","value":true},"expression":"147-8-147-37","instId":8},{"context":[{"name":"yearInt","value":1980}],"value":{"name":"angelic","value":true},"expression":"147-8-147-37","instId":2},{"context":[{"name":"yearInt","value":1980}],"value":{"name":"angelic","value":true},"expression":"147-8-147-37","instId":5},{"context":[{"name":"yearInt","value":1980}],"value":{"name":"angelic","value":true},"expression":"147-8-147-37","instId":7}]],
"1":[[{"context":[{"name":"yearInt","value":2009}],"value":{"name":"angelic","value":true},"expression":"147-8-147-37","instId":1},{"context":[{"name":"yearInt","value":2010}],"value":{"name":"angelic","value":true},"expression":"147-8-147-37","instId":4},{"context":[{"name":"yearInt","value":0}],"value":{"name":"angelic","value":true},"expression":"147-8-147-37","instId":10},{"context":[{"name":"yearInt","value":12}],"value":{"name":"angelic","value":true},"expression":"147-8-147-37","instId":3},{"context":[{"name":"yearInt","value":1979}],"value":{"name":"angelic","value":true},"expression":"147-8-147-37","instId":6},{"context":[{"name":"yearInt","value":1978}],"value":{"name":"angelic","value":true},"expression":"147-8-147-37","instId":0},{"context":[{"name":"yearInt","value":2010}],"value":{"name":"angelic","value":true},"expression":"147-8-147-37","instId":9},{"context":[{"name":"yearInt","value":2006}],"value":{"name":"angelic","value":true},"expression":"147-8-147-37","instId":8},{"context":[{"name":"yearInt","value":1980}],"value":{"name":"angelic","value":true},"expression":"147-8-147-37","instId":2},{"context":[{"name":"yearInt","value":2006}],"value":{"name":"angelic","value":true},"expression":"147-8-147-37","instId":5},{"context":[{"name":"yearInt","value":80}],"value":{"name":"angelic","value":true},"expression":"147-8-147-37","instId":7}],[{"context":[{"name":"yearInt","value":0}],"value":{"name":"angelic","value":true},"expression":"147-8-147-37","instId":11},{"context":[{"name":"yearInt","value":2009}],"value":{"name":"angelic","value":true},"expression":"147-8-147-37","instId":1},{"context":[{"name":"yearInt","value":2010}],"value":{"name":"angelic","value":false},"expression":"147-8-147-37","instId":4},{"context":[{"name":"yearInt","value":2010}],"value":{"name":"angelic","value":true},"expression":"147-8-147-37","instId":10},{"context":[{"name":"yearInt","value":12}],"value":{"name":"angelic","value":true},"expression":"147-8-147-37","instId":3},{"context":[{"name":"yearInt","value":2006}],"value":{"name":"angelic","value":true},"expression":"147-8-147-37","instId":6},{"context":[{"name":"yearInt","value":1978}],"value":{"name":"angelic","value":true},"expression":"147-8-147-37","instId":0},{"context":[{"name":"yearInt","value":2006}],"value":{"name":"angelic","value":true},"expression":"147-8-147-37","instId":9},{"context":[{"name":"yearInt","value":80}],"value":{"name":"angelic","value":true},"expression":"147-8-147-37","instId":8},{"context":[{"name":"yearInt","value":1980}],"value":{"name":"angelic","value":true},"expression":"147-8-147-37","instId":2},{"context":[{"name":"yearInt","value":20}],"value":{"name":"angelic","value":false},"expression":"147-8-147-37","instId":5},{"context":[{"name":"yearInt","value":1979}],"value":{"name":"angelic","value":true},"expression":"147-8-147-37","instId":7}]]

}